jobflow_remote/__init__.py
jobflow_remote/_version.py
jobflow_remote/py.typed
jobflow_remote/cli/__init__.py
jobflow_remote/cli/admin.py
jobflow_remote/cli/backup.py
jobflow_remote/cli/batch.py
jobflow_remote/cli/execution.py
jobflow_remote/cli/flow.py
jobflow_remote/cli/formatting.py
jobflow_remote/cli/gui.py
jobflow_remote/cli/jf.py
jobflow_remote/cli/jfr_typer.py
jobflow_remote/cli/job.py
jobflow_remote/cli/plugin.py
jobflow_remote/cli/project.py
jobflow_remote/cli/runner.py
jobflow_remote/cli/types.py
jobflow_remote/cli/utils.py
jobflow_remote/config/__init__.py
jobflow_remote/config/base.py
jobflow_remote/config/helper.py
jobflow_remote/config/jobconfig.py
jobflow_remote/config/manager.py
jobflow_remote/config/settings.py
jobflow_remote/jobs/__init__.py
jobflow_remote/jobs/batch.py
jobflow_remote/jobs/daemon.py
jobflow_remote/jobs/data.py
jobflow_remote/jobs/graph.py
jobflow_remote/jobs/jobcontroller.py
jobflow_remote/jobs/report.py
jobflow_remote/jobs/run.py
jobflow_remote/jobs/runner.py
jobflow_remote/jobs/state.py
jobflow_remote/jobs/store.py
jobflow_remote/jobs/submit.py
jobflow_remote/jobs/upgrade.py
jobflow_remote/remote/__init__.py
jobflow_remote/remote/data.py
jobflow_remote/remote/queue.py
jobflow_remote/remote/host/__init__.py
jobflow_remote/remote/host/base.py
jobflow_remote/remote/host/local.py
jobflow_remote/remote/host/remote.py
jobflow_remote/testing/__init__.py
jobflow_remote/testing/cli.py
jobflow_remote/utils/__init__.py
jobflow_remote/utils/data.py
jobflow_remote/utils/db.py
jobflow_remote/utils/examples.py
jobflow_remote/utils/log.py
jobflow_remote/utils/remote.py
jobflow_remote/utils/schedule.py
jobflow_remote/webgui/__init__.py
jobflow_remote/webgui/logo_jfr.png
jobflow_remote/webgui/style.css
jobflow_remote/webgui/webgui.py
jobflow_remote-1.0.0.dist-info/licenses/LICENSE
jobflow_remote-1.0.0.dist-info/METADATA
jobflow_remote-1.0.0.dist-info/WHEEL
jobflow_remote-1.0.0.dist-info/entry_points.txt
jobflow_remote-1.0.0.dist-info/top_level.txt
jobflow_remote-1.0.0.dist-info/RECORD
