Metadata-Version: 2.4
Name: jobflow-remote
Version: 1.0.0
Summary: Jobflow Remote is a Python package to run jobflow workflows on remote resources
Author-email: Guido Petretto <guido.petretto@matgenix.com>
License-Expression: BSD-3-Clause
Project-URL: homepage, https://Matgenix.github.io/jobflow-remote/
Project-URL: repository, https://github.com/Matgenix/jobflow-remote
Project-URL: documentation, https://Matgenix.github.io/jobflow-remote/
Project-URL: changelog, https://matgenix.github.io/jobflow-remote/changelog
Classifier: Development Status :: 5 - Production/Stable
Classifier: Intended Audience :: Information Technology
Classifier: Intended Audience :: Science/Research
Classifier: Intended Audience :: System Administrators
Classifier: Operating System :: OS Independent
Classifier: Programming Language :: Python :: 3
Classifier: Programming Language :: Python :: 3.10
Classifier: Programming Language :: Python :: 3.11
Classifier: Programming Language :: Python :: 3.12
Classifier: Programming Language :: Python :: 3.13
Classifier: Programming Language :: Python :: 3.14
Classifier: Topic :: Other/Nonlisted Topic
Classifier: Topic :: Scientific/Engineering
Requires-Python: !=3.14.1,>=3.10
License-File: LICENSE
Requires-Dist: fabric~=3.2
Requires-Dist: flufl.lock<10,>=8
Requires-Dist: psutil<8.0,>=5.9; python_version < "3.12"
Requires-Dist: psutil<8.0,>=6.0; python_version >= "3.12"
Requires-Dist: jobflow>=0.2.1
Requires-Dist: monty>=2024.7.12
Requires-Dist: pydantic>=2.4; python_version < "3.13"
Requires-Dist: pydantic>=2.8; python_version >= "3.13" and python_version < "3.14"
Requires-Dist: pydantic>=2.12; python_version >= "3.14"
Requires-Dist: pymongo<4.11,>=4.4
Requires-Dist: python-dateutil>=2.8.2
Requires-Dist: qtoolkit>=0.1.6
Requires-Dist: rich<15.0,>=13.7
Requires-Dist: ruamel.yaml>=0.17
Requires-Dist: schedule~=1.2
Requires-Dist: supervisor~=4.2; python_version < "3.12"
Requires-Dist: supervisor>=4.2.5; python_version >= "3.12"
Requires-Dist: tomlkit~=0.12
Requires-Dist: typer>=0.16
Provides-Extra: dev
Requires-Dist: pre-commit>=3.0.0; extra == "dev"
Provides-Extra: tests
Requires-Dist: docker~=7.0; extra == "tests"
Requires-Dist: pytest<10,>=8; extra == "tests"
Requires-Dist: pytest-cov<8,>=6; extra == "tests"
Requires-Dist: pytest-durations~=1.3; extra == "tests"
Requires-Dist: pytest-mock~=3.14; extra == "tests"
Requires-Dist: python-on-whales~=0.75; extra == "tests"
Requires-Dist: coverage>=7.10; extra == "tests"
Provides-Extra: docs
Requires-Dist: autodoc_pydantic>=2.0.0; extra == "docs"
Requires-Dist: pydata-sphinx-theme; extra == "docs"
Requires-Dist: sphinx; extra == "docs"
Requires-Dist: sphinx-copybutton; extra == "docs"
Requires-Dist: sphinx_design; extra == "docs"
Requires-Dist: sphinxcontrib-mermaid; extra == "docs"
Requires-Dist: sphinxcontrib-typer[html]; extra == "docs"
Requires-Dist: json-schema-for-humans; extra == "docs"
Provides-Extra: gui
Requires-Dist: python-fasthtml>=0.12.0; extra == "gui"
Dynamic: license-file
